pymaven/__init__.py
pymaven/artifact.py
pymaven/client.py
pymaven/constants.py
pymaven/errors.py
pymaven/pom.py
pymaven/utils.py
pymaven/versioning.py
pymaven_patch-0.3.2.dist-info/LICENSE
pymaven_patch-0.3.2.dist-info/METADATA
pymaven_patch-0.3.2.dist-info/WHEEL
pymaven_patch-0.3.2.dist-info/pbr.json
pymaven_patch-0.3.2.dist-info/top_level.txt
pymaven_patch-0.3.2.dist-info/RECORD
